{"dataset":{"0":"Antrac_2","1":"Antrac_2","10":"Antrac_Collapse_4","11":"Antrac_Collapse_4","12":"Antrac_2","13":"Collapse_2","14":"Collapse_2","2":"Collapse_2","3":"Collapse_2","4":"Antrac_Collapse_4","5":"Antrac_Collapse_4","6":"Antrac_2","7":"Collapse_2","8":"Antrac_Collapse_4","9":"Antrac_2"},"arch":{"0":"MLP","1":"LeNet-5","10":"LeNet-5","11":"MLP","12":"AlexNet","13":"MLP","14":"VGGNet-16","2":"LeNet-5","3":"Custom","4":"Custom","5":"VGGNet-16","6":"MLP_extra","7":"AlexNet","8":"AlexNet","9":"VGGNet-16"},"loss":{"0":0.1872648726,"1":0.2798412281,"10":1.9038465885,"11":1.3040885925,"12":0.353898491,"13":0.6067646505,"14":1.3687279723,"2":0.663537526,"3":0.610463317,"4":0.9073541342,"5":1.6329376106,"6":0.2245243986,"7":1.8026627936,"8":1.1747966557,"9":0.2856870119},"acc":{"0":0.9516128517,"1":0.9374999485,"10":0.7142856628,"11":0.7070706557,"12":0.9291338068,"13":0.774509754,"14":0.6914893111,"2":0.7559808116,"3":0.783783735,"4":0.7999999485,"5":0.7070706557,"6":0.9090908578,"7":0.7368420557,"8":0.7962962454,"9":0.9062499486},"notes":{"0":"using F1-score as acc","1":"acc=F1-score","10":"acc=F1, imgsize=32px","11":"acc=F1, imgsize=32px","12":"acc=F1-score","13":"F1-Score, img=64px","14":"acc=F1, imgsize=64px","2":"F1-Score, img=64px","3":"F1-Score, img=64px","4":"F1-Score, img=512px","5":"acc=F1, imgsize=64px","6":"acc=F1, imgsize=32px","7":"acc=F1, imgsize=256px","8":"acc=F1, imgsize=256px","9":"acc=F1, imgsize=64px"}}